dependency_detective/__init__.py
dependency_detective/dependency_detective.py
dependency_detective-0.1.1.dist-info/LICENSE
dependency_detective-0.1.1.dist-info/METADATA
dependency_detective-0.1.1.dist-info/WHEEL
dependency_detective-0.1.1.dist-info/entry_points.txt
dependency_detective-0.1.1.dist-info/top_level.txt
dependency_detective-0.1.1.dist-info/RECORD
